gmt/__init__.py
gmt/_base_client.py
gmt/_client.py
gmt/_compat.py
gmt/_constants.py
gmt/_exceptions.py
gmt/_files.py
gmt/_models.py
gmt/_qs.py
gmt/_resource.py
gmt/_response.py
gmt/_streaming.py
gmt/_types.py
gmt/_version.py
gmt/pagination.py
gmt/py.typed
gmt/_utils/__init__.py
gmt/_utils/_compat.py
gmt/_utils/_datetime_parse.py
gmt/_utils/_json.py
gmt/_utils/_logs.py
gmt/_utils/_proxy.py
gmt/_utils/_reflection.py
gmt/_utils/_resources_proxy.py
gmt/_utils/_streams.py
gmt/_utils/_sync.py
gmt/_utils/_transform.py
gmt/_utils/_typing.py
gmt/_utils/_utils.py
gmt/lib/.keep
gmt/resources/__init__.py
gmt/resources/accounts.py
gmt/resources/profile.py
gmt/resources/purchases.py
gmt/resources/service.py
gmt/resources/webhooks.py
gmt/types/__init__.py
gmt/types/account_list_countries_params.py
gmt/types/account_list_countries_response.py
gmt/types/account_list_params.py
gmt/types/account_list_response.py
gmt/types/account_retrieve_response.py
gmt/types/profile_retrieve_response.py
gmt/types/purchase_create_params.py
gmt/types/purchase_create_response.py
gmt/types/purchase_list_params.py
gmt/types/purchase_list_response.py
gmt/types/purchase_refund_response.py
gmt/types/purchase_request_verification_code_params.py
gmt/types/purchase_request_verification_code_response.py
gmt/types/purchase_retrieve_response.py
gmt/types/service_get_server_time_response.py
gmt/types/service_health_check_response.py
gmt/types/webhook_test_params.py
gmt/types/webhook_test_response.py
gmt_python_sdk-0.14.0.dist-info/METADATA
gmt_python_sdk-0.14.0.dist-info/WHEEL
gmt_python_sdk-0.14.0.dist-info/licenses/LICENSE
gmt_python_sdk-0.14.0.dist-info/RECORD
